lol_monitor.py
lol_monitor-1.8.dist-info/licenses/LICENSE
lol_monitor-1.8.dist-info/METADATA
lol_monitor-1.8.dist-info/WHEEL
lol_monitor-1.8.dist-info/entry_points.txt
lol_monitor-1.8.dist-info/top_level.txt
lol_monitor-1.8.dist-info/RECORD
