Metadata-Version: 2.4
Name: lol_monitor
Version: 1.8
Summary: Tool implementing real-time tracking of LoL (League of Legends) players activities
Author-email: Michal Szymanski <misiektoja-pypi@rm-rf.ninja>
License-Expression: GPL-3.0-or-later
Project-URL: Homepage, https://github.com/misiektoja/lol_monitor
Project-URL: Source, https://github.com/misiektoja/lol_monitor
Project-URL: Changelog, https://github.com/misiektoja/lol_monitor/blob/main/RELEASE_NOTES.md
Keywords: lol,riot,league-of-legends,monitoring,tracking,real-time,osint,pulsefire
Classifier: Programming Language :: Python :: 3
Classifier: Operating System :: OS Independent
Classifier: Operating System :: Microsoft :: Windows
Classifier: Operating System :: POSIX :: Linux
Classifier: Operating System :: MacOS :: MacOS X
Requires-Python: >=3.12
License-File: LICENSE
Requires-Dist: pulsefire>=2.0.9
Requires-Dist: requests>=2.0
Requires-Dist: python-dateutil>=2.8
Requires-Dist: python-dotenv>=0.19
Dynamic: license-file
